jkeydb/__init__.py
jkeydb-0.3.0.dist-info/LICENSE
jkeydb-0.3.0.dist-info/METADATA
jkeydb-0.3.0.dist-info/WHEEL
jkeydb-0.3.0.dist-info/top_level.txt
jkeydb-0.3.0.dist-info/RECORD
