Metadata-Version: 2.1
Name: jkeydb
Version: 0.3.0
Summary: a simple key-value database
Author: The DT
Author-email: The DT <duongtuan30306@gmail.com>
License: Apache License
Project-URL: Homepage, https://github.com/duongtuan303030/jkeydb
Project-URL: Bug Tracker, https://github.com/duongtuan303030/jkeydb/issues
Requires-Python: >=3.7
License-File: LICENSE
